crf/__init__.py
torchcrf/__init__.py
pytorch_crf-0.7.2.dist-info/LICENSE.txt
pytorch_crf-0.7.2.dist-info/METADATA
pytorch_crf-0.7.2.dist-info/WHEEL
pytorch_crf-0.7.2.dist-info/top_level.txt
pytorch_crf-0.7.2.dist-info/RECORD
