Metadata-Version: 2.1
Name: pytorch-crf
Version: 0.7.2
Summary: Conditional random field in PyTorch
Home-page: https://github.com/kmkurn/pytorch-crf
Author: Kemal Kurniawan
Author-email: kemal@kkurniawan.com
License: MIT
Keywords: torch
Platform: UNKNOWN
Classifier: Development Status :: 4 - Beta
Classifier: Intended Audience :: Developers
Classifier: Intended Audience :: Science/Research
Classifier: License :: OSI Approved :: MIT License
Classifier: Programming Language :: Python :: 3.6
Classifier: Programming Language :: Python :: 3.7
Requires-Python: >=3.6, <4
